_sequenzo_fastcluster.cpython-311-x86_64-linux-gnu.so
sequenzo/__init__.py
sequenzo/define_sequence_data.py
sequenzo/openmp_setup.py
sequenzo/version_check.py
sequenzo/big_data/__init__.py
sequenzo/big_data/clara/__init__.py
sequenzo/big_data/clara/clara.py
sequenzo/big_data/clara/visualization.py
sequenzo/big_data/clara/utils/__init__.py
sequenzo/big_data/clara/utils/aggregatecases.py
sequenzo/big_data/clara/utils/davies_bouldin.py
sequenzo/big_data/clara/utils/get_weighted_diss.cpython-311-x86_64-linux-gnu.so
sequenzo/big_data/clara/utils/wfcmdd.py
sequenzo/clustering/KMedoids.py
sequenzo/clustering/__init__.py
sequenzo/clustering/clustering_c_code.cpython-311-x86_64-linux-gnu.so
sequenzo/clustering/hierarchical_clustering.py
sequenzo/clustering/sequenzo_fastcluster/fastcluster.py
sequenzo/clustering/sequenzo_fastcluster/src/fastcluster.cpp
sequenzo/clustering/sequenzo_fastcluster/src/fastcluster_python.cpp
sequenzo/clustering/src/KMedoid.cpp
sequenzo/clustering/src/PAM.cpp
sequenzo/clustering/src/PAMonce.cpp
sequenzo/clustering/src/cluster_quality.cpp
sequenzo/clustering/src/cluster_quality.h
sequenzo/clustering/src/cluster_quality_backup.cpp
sequenzo/clustering/src/module.cpp
sequenzo/clustering/src/weightedinertia.cpp
sequenzo/clustering/utils/__init__.py
sequenzo/clustering/utils/disscenter.py
sequenzo/data_preprocessing/__init__.py
sequenzo/data_preprocessing/helpers.py
sequenzo/datasets/__init__.py
sequenzo/datasets/biofam.csv
sequenzo/datasets/biofam_child_domain.csv
sequenzo/datasets/biofam_left_domain.csv
sequenzo/datasets/biofam_married_domain.csv
sequenzo/datasets/chinese_colonial_territories.csv
sequenzo/datasets/country_co2_emissions.csv
sequenzo/datasets/country_co2_emissions_global_deciles.csv
sequenzo/datasets/country_co2_emissions_global_quintiles.csv
sequenzo/datasets/country_co2_emissions_local_deciles.csv
sequenzo/datasets/country_co2_emissions_local_quintiles.csv
sequenzo-0.1.31.dist-info/METADATA
sequenzo-0.1.31.dist-info/WHEEL
sequenzo-0.1.31.dist-info/top_level.txt
sequenzo-0.1.31.dist-info/RECORD
sequenzo-0.1.31.dist-info/licenses/LICENSE
