Metadata-Version: 2.4
Name: sequenzo
Version: 0.1.31
Summary: A fast, scalable and intuitive Python package for social sequence analysis.
Author-email: Yuqi Liang <yuqi.liang.1900@gmail.com>, Xinyi Li <1836724126@qq.com>, Jan Heinrich Ernst Meyerhoff-Liang <jan.meyerhoff1@gmail.com>
License: BSD 3-Clause License
Project-URL: Homepage, https://github.com/Liang-Team/Sequenzo
Project-URL: Documentation, https://sequenzo.yuqi-liang.tech
Classifier: Development Status :: 3 - Alpha
Classifier: Intended Audience :: Science/Research
Classifier: Intended Audience :: Developers
Classifier: Programming Language :: Python :: 3.9
Classifier: Programming Language :: Python :: 3.10
Classifier: Programming Language :: Python :: 3.11
Classifier: Programming Language :: Python :: 3.12
Requires-Python: <3.13,>=3.9
License-File: LICENSE
Requires-Dist: numpy>=1.21.0
Requires-Dist: pandas>=1.2.5
Requires-Dist: matplotlib>=3.4.3
Requires-Dist: seaborn>=0.11.2
Requires-Dist: Pillow>=8.3.2
Requires-Dist: pybind11>=2.6.0
Requires-Dist: cython>=0.29.21
Requires-Dist: scipy<1.17,>=1.6.3
Requires-Dist: scikit-learn>=0.24.2
Requires-Dist: joblib>=1.0.1
Requires-Dist: docutils>=0.17
Requires-Dist: tqdm<5.0.0,>=4.62.3
Requires-Dist: missingno<0.6.0,>=0.5.2
Requires-Dist: cffi>=1.15.0
Requires-Dist: hmmlearn>=0.2.0
Provides-Extra: dev
Requires-Dist: pytest>=6.2.5; extra == "dev"
Requires-Dist: flake8>=3.9.2; extra == "dev"
Dynamic: license-file
